probecheck/__init__.py
probecheck/common/sql_pool.py
probecheck/common/validate_configs.py
probecheck/core.py
probecheck/tools/benchmark.py
probecheck/tools/dashborad.py
probecheck/tools/test_results.db
probecheck/utils.py
probecheck-0.1.0.dist-info/entry_points.txt
probecheck-0.1.0.dist-info/METADATA
probecheck-0.1.0.dist-info/WHEEL
probecheck-0.1.0.dist-info/RECORD
