Metadata-Version: 2.1
Name: probecheck
Version: 0.1.0
Summary: A modern, advanced testing framework for probing and validating complex systems.
Home-page: https://github.com/letalboy/probecheck
License: MIT
Author: Cristian Camargo
Author-email: ccf@cdone.com.br
Requires-Python: >=3.10,<4.0
Classifier: License :: OSI Approved :: MIT License
Classifier: Programming Language :: Python :: 3
Classifier: Programming Language :: Python :: 3.10
Classifier: Programming Language :: Python :: 3.11
Classifier: Programming Language :: Python :: 3.12
Requires-Dist: pandas (>=2.2.2,<3.0.0)
Requires-Dist: toml (>=0.10.2,<0.11.0)
Project-URL: Documentation, https://github.com/letalboy/probecheck#readme
Project-URL: Repository, https://github.com/letalboy/probecheck
